jyquickhelper/__init__.py
jyquickhelper/helper_in_notebook.py
jyquickhelper/js/__init__.py
jyquickhelper/js/c3/__init__.py
jyquickhelper/js/custom/__init__.py
jyquickhelper/js/cytoscape/__init__.py
jyquickhelper/js/d3/__init__.py
jyquickhelper/js/eve/__init__.py
jyquickhelper/js/mermaid/__init__.py
jyquickhelper/js/pig/__init__.py
jyquickhelper/js/raphael/__init__.py
jyquickhelper/js/renderjson/LICENSE.txt
jyquickhelper/js/renderjson/__init__.py
jyquickhelper/js/renderjson/renderjson.css
jyquickhelper/js/renderjson/renderjson.js
jyquickhelper/js/svg/__init__.py
jyquickhelper/js/svgpanzoom/__init__.py
jyquickhelper/js/treant/__init__.py
jyquickhelper/js/visjs/LICENSE-APACHE-2.0.txt
jyquickhelper/js/visjs/LICENSE-MIT.txt
jyquickhelper/js/visjs/__init__.py
jyquickhelper/js/visjs/vis-graph3d.min.js
jyquickhelper/js/visjs/vis-network.min.css
jyquickhelper/js/visjs/vis-network.min.js
jyquickhelper/js/visjs/vis-timeline-graph2d.min.css
jyquickhelper/js/visjs/vis-timeline-graph2d.min.js
jyquickhelper/js/visjs/vis.min.css
jyquickhelper/js/visjs/vis.min.js
jyquickhelper/js/vizjs/LICENSE.txt
jyquickhelper/js/vizjs/__init__.py
jyquickhelper/js/vizjs/viz-lite.js
jyquickhelper/js/vizjs/viz.js
jyquickhelper/jspy/__init__.py
jyquickhelper/jspy/render_nb_js.py
jyquickhelper/jspy/render_nb_js_dot.py
jyquickhelper/jspy/render_nb_js_vis.py
jyquickhelper/jspy/render_nb_json.py
jyquickhelper-0.4.220.dist-info/LICENSE.txt
jyquickhelper-0.4.220.dist-info/METADATA
jyquickhelper-0.4.220.dist-info/WHEEL
jyquickhelper-0.4.220.dist-info/top_level.txt
jyquickhelper-0.4.220.dist-info/RECORD
