Metadata-Version: 2.1
Name: jyquickhelper
Version: 0.4.220
Summary: Helpers for Jupyter notebooks: automated menu, JSON visualizer, plug javascript
Home-page: http://www.xavierdupre.fr/app/jyquickhelper/helpsphinx/index.html
Author: Xavier Dupré
Author-email: xavier.dupre@gmail.com
License: MIT
Download-URL: https://github.com/sdpython/jyquickhelper/
Keywords: jyquickhelper,Xavier Dupré
Platform: UNKNOWN
Classifier: Programming Language :: Python :: 3
Classifier: Intended Audience :: Developers
Classifier: Topic :: Scientific/Engineering
Classifier: Topic :: Education
Classifier: License :: OSI Approved :: MIT License
Classifier: Development Status :: 5 - Production/Stable
Requires-Dist: ipython
Requires-Dist: jupyter
Requires-Dist: notebook
